pymtr/__init__.py
pymtr/main.py
pymtr-1.0.1.dist-info/METADATA
pymtr-1.0.1.dist-info/WHEEL
pymtr-1.0.1.dist-info/entry_points.txt
pymtr-1.0.1.dist-info/top_level.txt
pymtr-1.0.1.dist-info/RECORD
