Metadata-Version: 2.1
Name: pymtr
Version: 1.0.1
Summary: A Python process monitoring tool
Home-page: UNKNOWN
Author: Artem Bolshakov
Author-email: artemis4650@gmail.com
License: UNKNOWN
Platform: UNKNOWN
Requires-Dist: matplotlib
Requires-Dist: psutil
